{"chunk_definitions":[{"row":9,"row_count":1,"visible":true,"expansion_state":0,"options":{"engine":"r","label":"setup","include":false},"document_id":"4A7F9507","chunk_id":"csetup_chunk","chunk_label":"setup"},{"row":35,"row_count":1,"visible":true,"expansion_state":0,"options":{"engine":"r","label":"Libraries","include":false},"document_id":"4A7F9507","chunk_id":"cgusrf3nbjewu","chunk_label":"Libraries"},{"row":116,"row_count":1,"visible":true,"expansion_state":0,"options":{"engine":"r","label":"Reading_in_data"},"document_id":"4A7F9507","chunk_id":"c34ul6o1aiht6","chunk_label":"Reading_in_data"},{"row":140,"row_count":1,"visible":true,"expansion_state":0,"options":{},"document_id":"4A7F9507","chunk_id":"chowdfqdym37f","chunk_label":"subset for stat analy"},{"row":155,"row_count":1,"visible":true,"expansion_state":0,"options":{},"document_id":"4A7F9507","chunk_id":"cfjh112k8nrxj","chunk_label":"f test age"},{"row":165,"row_count":1,"visible":true,"expansion_state":0,"options":{},"document_id":"4A7F9507","chunk_id":"ciqk4pazfju2j","chunk_label":"t test age"},{"row":183,"row_count":1,"visible":true,"expansion_state":0,"options":{},"document_id":"4A7F9507","chunk_id":"c017h7d57k0ot","chunk_label":"f test tumor size"},{"row":190,"row_count":1,"visible":true,"expansion_state":0,"options":{},"document_id":"4A7F9507","chunk_id":"cggms017jxohy","chunk_label":"t test tumor size"},{"row":208,"row_count":1,"visible":true,"expansion_state":0,"options":{},"document_id":"4A7F9507","chunk_id":"c0kk7bjnr7p74","chunk_label":"f test overall survival month"},{"row":217,"row_count":1,"visible":true,"expansion_state":0,"options":{},"document_id":"4A7F9507","chunk_id":"ckiydj9ezmy9t","chunk_label":"t test overall survival month"}],"doc_write_time":1697248071}